mcp_web_tools/__init__.py
mcp_web_tools/loaders.py
mcp_web_tools/search.py
mcp_web_tools-0.9.1.dist-info/METADATA
mcp_web_tools-0.9.1.dist-info/WHEEL
mcp_web_tools-0.9.1.dist-info/entry_points.txt
mcp_web_tools-0.9.1.dist-info/RECORD
