Metadata-Version: 2.4
Name: mcp-web-tools
Version: 0.9.1
Summary: A powerful MCP server to equip LLMs with web access, search, and content extraction capabilities
Project-URL: Homepage, https://github.com/pietz/mcp-web-tools
Project-URL: Issues, https://github.com/pietz/mcp-web-tools/issues
Author-email: Paul-Louis Pröve <mail@plpp.de>
License: MIT
Keywords: extraction,llm,mcp,pdf,search,web
Classifier: Development Status :: 4 - Beta
Classifier: Intended Audience :: Developers
Classifier: License :: OSI Approved :: MIT License
Classifier: Programming Language :: Python :: 3
Classifier: Programming Language :: Python :: 3.12
Classifier: Topic :: Internet :: WWW/HTTP
Classifier: Topic :: Software Development :: Libraries :: Python Modules
Classifier: Topic :: Text Processing :: Markup
Requires-Python: >=3.12
Requires-Dist: duckduckgo-search>=8.1.1
Requires-Dist: googlesearch-python>=1.3.0
Requires-Dist: httpx>=0.28.1
Requires-Dist: mcp>=1.13.1
Requires-Dist: perplexityai>=0.11.0
Requires-Dist: pillow>=11.2.1
Requires-Dist: psutil>=7.0.0
Requires-Dist: pymupdf4llm>=0.0.27
Requires-Dist: trafilatura>=2.0.0
Requires-Dist: zendriver>=0.14.0
